ingot_rabbitmq/__init__.py
ingot_rabbitmq/bootstrap/__init__.py
ingot_rabbitmq/bootstrap/base.py
ingot_rabbitmq/bootstrap/scaffolding/__init__.py
ingot_rabbitmq/scripts/__init__.py
ingot_rabbitmq/scripts/ingot_rabbitmq.py
ingot_rabbitmq/tests/__init__.py
ingot_rabbitmq/tests/functionals/__init__.py
ingot_rabbitmq/tests/units/__init__.py
ingot_rabbitmq/tests/units/bootstrap/__init__.py
ingot_rabbitmq/tests/units/bootstrap/test_base.py
ingot_rabbitmq/tests/units/scripts/__init__.py
ingot_rabbitmq/tests/units/scripts/test_ingot_rabbitmq.py
scripts/__init__.py
scripts/create_package_version_file.py
ingot_rabbitmq-0.1.0.dist-info/LICENSE
ingot_rabbitmq-0.1.0.dist-info/METADATA
ingot_rabbitmq-0.1.0.dist-info/WHEEL
ingot_rabbitmq-0.1.0.dist-info/entry_points.txt
ingot_rabbitmq-0.1.0.dist-info/top_level.txt
ingot_rabbitmq-0.1.0.dist-info/RECORD
