Metadata-Version: 2.1
Name: ingot-rabbitmq
Version: 0.1.0
Summary: Provides functionality for working with the RabbitMQ tool
Home-page: https://github.com/ABKorotky/ingot-rabbitmq.git
Author: Alexander Korotkiy
Author-email: abkorotky@gmail.com
License: UNKNOWN
Platform: UNKNOWN
Classifier: Development Status :: 1 - Planning
Classifier: Environment :: Web Environment
Classifier: Framework :: AsyncIO
Classifier: Intended Audience :: Developers
Classifier: License :: OSI Approved :: GNU General Public License (GPL)
Classifier: Natural Language :: English
Classifier: Operating System :: POSIX
Classifier: Operating System :: POSIX :: Linux
Classifier: Programming Language :: Python
Classifier: Programming Language :: Python :: 3.8
Classifier: Topic :: Internet
Requires-Dist: ingots (~=0.12.0)
